cf_guidance/__init__.py
cf_guidance/_modidx.py
cf_guidance/schedules.py
cf_guidance/transforms.py
cf_guidance-0.0.3.dist-info/LICENSE
cf_guidance-0.0.3.dist-info/METADATA
cf_guidance-0.0.3.dist-info/WHEEL
cf_guidance-0.0.3.dist-info/entry_points.txt
cf_guidance-0.0.3.dist-info/top_level.txt
cf_guidance-0.0.3.dist-info/RECORD
