Metadata-Version: 2.1
Name: cf-guidance
Version: 0.0.3
Summary: Transforms for Classifier-free Guidance
Home-page: https://github.com/enzokro/guidance_transforms
Author: enzokro
Author-email: christopher.kroenke@gmail.com
License: Apache Software License 2.0
Keywords: nbdev jupyter notebook python
Classifier: Development Status :: 4 - Beta
Classifier: Intended Audience :: Developers
Classifier: Natural Language :: English
Classifier: Programming Language :: Python :: 3.7
Classifier: Programming Language :: Python :: 3.8
Classifier: Programming Language :: Python :: 3.9
Classifier: Programming Language :: Python :: 3.10
Classifier: License :: OSI Approved :: Apache Software License
Requires-Python: >=3.7
License-File: LICENSE
Requires-Dist: torch (>=1.7)
Provides-Extra: dev
